operator_learning/__init__.py
operator_learning/linalg.py
operator_learning/structs.py
operator_learning/utils.py
operator_learning/kernel/__init__.py
operator_learning/kernel/base.py
operator_learning/kernel/principal_components.py
operator_learning/kernel/reduced_rank.py
operator_learning/nn/__init__.py
operator_learning/nn/base.py
operator_learning/nn/functional.py
operator_learning/nn/linalg.py
operator_learning/nn/modules/__init__.py
operator_learning/nn/modules/losses.py
operator_learning-0.1.0.dist-info/METADATA
operator_learning-0.1.0.dist-info/WHEEL
operator_learning-0.1.0.dist-info/RECORD
