Metadata-Version: 2.4
Name: operator-learning
Version: 0.1.0
Summary: Add your description here
Author-email: Pietro Novelli <pietronvll@gmail.com>
Requires-Python: >=3.10
Requires-Dist: numpy>=1.25
Requires-Dist: scipy>=1.12
Requires-Dist: torch>=2.0
